[
  {
    "ContainingType": "cashreg.Controllers.ProductController",
    "Method": "GetAllProducts",
    "RelativePath": "api/Product",
    "HttpMethod": "GET",
    "IsController": true,
    "Order": 0,
    "Parameters": [],
    "ReturnTypes": [
      {
        "Type": "System.Collections.Generic.List\u00601[[cashreg.Models.DTOS.ProductsDTO, cashreg, Version=1.0.0.0, Culture=neutral, PublicKeyToken=null]]",
        "MediaTypes": [
          "text/plain",
          "application/json",
          "text/json"
        ],
        "StatusCode": 200
      }
    ]
  },
  {
    "ContainingType": "cashreg.Controllers.ProductController",
    "Method": "CreateTicketWithProducts",
    "RelativePath": "api/Product/create-ticket",
    "HttpMethod": "POST",
    "IsController": true,
    "Order": 0,
    "Parameters": [
      {
        "Name": "ticketDto",
        "Type": "cashreg.Models.DTOS.CreateTicketDTO",
        "IsRequired": true
      }
    ],
    "ReturnTypes": []
  },
  {
    "ContainingType": "cashreg.Controllers.ProductController",
    "Method": "GetAllStores",
    "RelativePath": "api/Product/store",
    "HttpMethod": "GET",
    "IsController": true,
    "Order": 0,
    "Parameters": [],
    "ReturnTypes": [
      {
        "Type": "System.Collections.Generic.List\u00601[[cashreg.Models.DTOS.StoreDTO, cashreg, Version=1.0.0.0, Culture=neutral, PublicKeyToken=null]]",
        "MediaTypes": [
          "text/plain",
          "application/json",
          "text/json"
        ],
        "StatusCode": 200
      }
    ]
  },
  {
    "ContainingType": "cashreg.Controllers.ProductController",
    "Method": "GetAllTickets",
    "RelativePath": "api/Product/ticket",
    "HttpMethod": "GET",
    "IsController": true,
    "Order": 0,
    "Parameters": [],
    "ReturnTypes": [
      {
        "Type": "System.Collections.Generic.List\u00601[[cashreg.Models.DTOS.TicketDTO2, cashreg, Version=1.0.0.0, Culture=neutral, PublicKeyToken=null]]",
        "MediaTypes": [
          "text/plain",
          "application/json",
          "text/json"
        ],
        "StatusCode": 200
      }
    ]
  },
  {
    "ContainingType": "cashreg.Controllers.ProductController",
    "Method": "GetAllTotal",
    "RelativePath": "api/Product/total",
    "HttpMethod": "GET",
    "IsController": true,
    "Order": 0,
    "Parameters": [],
    "ReturnTypes": [
      {
        "Type": "System.Collections.Generic.List\u00601[[cashreg.Models.DTOS.TotalProductLinkDTO2, cashreg, Version=1.0.0.0, Culture=neutral, PublicKeyToken=null]]",
        "MediaTypes": [
          "text/plain",
          "application/json",
          "text/json"
        ],
        "StatusCode": 200
      }
    ]
  }
]